{
  "run_time": "2026-07-24 21:23 IST",
  "run_epoch": 1784908400.1980217,
  "tickers": {
    "AKUMS": {
      "name": "Akums Drugs & Pharmaceuticals Ltd",
      "sector": "Healthcare",
      "close": 687.3,
      "flag": "Trend",
      "trend_template_score": "8/8"
    },
    "RPTECH": {
      "name": "Rashi Peripherals Ltd",
      "sector": "Information Technology",
      "close": 779.85,
      "flag": "Trend",
      "trend_template_score": "8/8"
    },
    "INOXINDIA": {
      "name": "Inox India Ltd",
      "sector": "Capital Goods",
      "close": 2004,
      "flag": "Trend",
      "trend_template_score": "8/8"
    },
    "RATNAVEER": {
      "name": "Ratnaveer Precision Engineering Ltd",
      "sector": "Capital Goods",
      "close": 178.61,
      "flag": "Trend",
      "trend_template_score": "8/8"
    },
    "IDEAFORGE": {
      "name": "Ideaforge Technology Ltd",
      "sector": "Capital Goods",
      "close": 870.65,
      "flag": "Trend",
      "trend_template_score": "8/8"
    },
    "AVALON": {
      "name": "Avalon Technologies Ltd",
      "sector": "Capital Goods",
      "close": 1741.5,
      "flag": "Trend",
      "trend_template_score": "8/8"
    },
    "AEROENTER": {
      "name": "Aeroflex Enterprises Ltd",
      "sector": "Capital Goods",
      "close": 127.3,
      "flag": "Trend",
      "trend_template_score": "8/8"
    },
    "SBCL": {
      "name": "Shivalik Bimetal Controls Ltd",
      "sector": "Capital Goods",
      "close": 755.7,
      "flag": "Trend",
      "trend_template_score": "8/8"
    },
    "CONFIPET": {
      "name": "Confidence Petroleum India Ltd",
      "sector": "Oil, Gas &amp; Consumable Fuels",
      "close": 78.3,
      "flag": "Trend",
      "trend_template_score": "8/8"
    },
    "SILVERTUC": {
      "name": "Silver Touch Technologies Ltd",
      "sector": "Information Technology",
      "close": 200.14,
      "flag": "Trend",
      "trend_template_score": "3/8"
    },
    "SIS": {
      "name": "Security & Intelligence Services India",
      "sector": "Consumer Services",
      "close": 437.55,
      "flag": "Trend",
      "trend_template_score": "8/8"
    },
    "CUPID": {
      "name": "Cupid Limited",
      "sector": "Fast Moving Consumer Goods",
      "close": 213.43,
      "flag": "Trend",
      "trend_template_score": "8/8"
    },
    "SCHNEIDER": {
      "name": "Schneider Electric Infrastructure Limited",
      "sector": "Capital Goods",
      "close": 1352.6,
      "flag": "Trend",
      "trend_template_score": "8/8"
    },
    "PANAMAPET": {
      "name": "Panama Petrochem Limited",
      "sector": "Oil, Gas &amp; Consumable Fuels",
      "close": 498.25,
      "flag": "Trend",
      "trend_template_score": "8/8"
    },
    "ADFFOODS": {
      "name": "Adf Foods Limited",
      "sector": "Fast Moving Consumer Goods",
      "close": 307.05,
      "flag": "Trend",
      "trend_template_score": "8/8"
    },
    "THANGAMAYL": {
      "name": "Thangamayil Jewellery Limited",
      "sector": "Consumer Durables",
      "close": 6906.5,
      "flag": "Trend",
      "trend_template_score": "8/8"
    },
    "ICIL": {
      "name": "Indo Count Industries Limited",
      "sector": "Textiles",
      "close": 403.45,
      "flag": "Trend",
      "trend_template_score": "8/8"
    },
    "ASTRAMICRO": {
      "name": "Astra Microwave Products Limited",
      "sector": "Capital Goods",
      "close": 1813.4,
      "flag": "Trend",
      "trend_template_score": "8/8"
    },
    "BHAGYANGR": {
      "name": "Bhagyanagar India",
      "sector": "Metals &amp; Mining",
      "close": 410.9,
      "flag": "Trend",
      "trend_template_score": "8/8"
    },
    "AEGISLOG": {
      "name": "Aegis Logistics Ltd",
      "sector": "Oil, Gas &amp; Consumable Fuels",
      "close": 1349.6,
      "flag": "Trend",
      "trend_template_score": "8/8"
    },
    "UNIVCABLES": {
      "name": "Universal Cables Limited",
      "sector": "Capital Goods",
      "close": 1234.8,
      "flag": "Trend",
      "trend_template_score": "8/8"
    },
    "MOTHERSON": {
      "name": "Samvardhana Motherson International Ltd",
      "sector": "Automobile and Auto Components",
      "close": 145.55,
      "flag": "Trend",
      "trend_template_score": "8/8"
    },
    "SIEMENS": {
      "name": "Siemens Limited",
      "sector": "Capital Goods",
      "close": 3689.8,
      "flag": "Trend",
      "trend_template_score": "7/8"
    },
    "EICHERMOT": {
      "name": "Eicher Motors Limited",
      "sector": "Automobile and Auto Components",
      "close": 7628,
      "flag": "Trend",
      "trend_template_score": "8/8"
    },
    "TITAN": {
      "name": "Titan Company Limited",
      "sector": "Consumer Durables",
      "close": 4677,
      "flag": "Trend",
      "trend_template_score": "8/8"
    },
    "FEDERALBNK": {
      "name": "The Federal Bank  Limited",
      "sector": "Financial Services",
      "close": 354.3,
      "flag": "Trend",
      "trend_template_score": "8/8"
    },
    "BELRISE": {
      "name": "Belrise Industries Ltd",
      "sector": "Automobile and Auto Components",
      "close": 228.26,
      "flag": "Watch",
      "trend_template_score": "8/8"
    },
    "SENORES": {
      "name": "Senores Pharmaceuticals Ltd",
      "sector": "Healthcare",
      "close": 1387.5,
      "flag": "Watch",
      "trend_template_score": "8/8"
    },
    "SAILIFE": {
      "name": "Sai Life Sciences Ltd",
      "sector": "Healthcare",
      "close": 1232.9,
      "flag": "Watch",
      "trend_template_score": "8/8"
    },
    "ACMESOLAR": {
      "name": "ACME Solar Holdings Ltd",
      "sector": "Power",
      "close": 365.85,
      "flag": "Watch",
      "trend_template_score": "8/8"
    },
    "GROWWDEFNC": {
      "name": "Groww Nifty India Defence ETF",
      "sector": null,
      "close": 93.47,
      "flag": "Watch",
      "trend_template_score": "8/8"
    },
    "MODEFENCE": {
      "name": "Motilal Oswal Nifty India Defence ETF",
      "sector": null,
      "close": 102.55,
      "flag": "Watch",
      "trend_template_score": "8/8"
    },
    "DEEDEV": {
      "name": "DEE Development Engineers Ltd",
      "sector": "Capital Goods",
      "close": 653.45,
      "flag": "Watch",
      "trend_template_score": "8/8"
    },
    "JNKINDIA": {
      "name": "JNK India Ltd",
      "sector": "Capital Goods",
      "close": 470.9,
      "flag": "Watch",
      "trend_template_score": "8/8"
    },
    "RISHABH": {
      "name": "Rishabh Instruments Ltd",
      "sector": "Capital Goods",
      "close": 622.3,
      "flag": "Watch",
      "trend_template_score": "8/8"
    },
    "SYRMA": {
      "name": "Syrma SGS Technology Ltd",
      "sector": "Capital Goods",
      "close": 1288.3,
      "flag": "Watch",
      "trend_template_score": "8/8"
    },
    "AETHER": {
      "name": "Aether Industries Ltd",
      "sector": "Chemicals",
      "close": 1427.5,
      "flag": "Watch",
      "trend_template_score": "8/8"
    },
    "IONEXCHANG": {
      "name": "Ion Exchange (India) Ltd",
      "sector": "Utilities",
      "close": 425.1,
      "flag": "Watch",
      "trend_template_score": "8/8"
    },
    "MONQ50": {
      "name": "Motilal Oswal Nasdaq Q 50 ETF",
      "sector": null,
      "close": 142.45,
      "flag": "Watch",
      "trend_template_score": "8/8"
    },
    "ANANDRATHI": {
      "name": "Anand Rathi Wealth Ltd",
      "sector": "Financial Services",
      "close": 2042.1,
      "flag": "Watch",
      "trend_template_score": "8/8"
    },
    "STARHEALTH": {
      "name": "Star Health & Allied Insurance Company Ltd",
      "sector": "Financial Services",
      "close": 580.8,
      "flag": "Watch",
      "trend_template_score": "8/8"
    },
    "SBC": {
      "name": "SBC Exports Ltd",
      "sector": "Textiles",
      "close": 42.07,
      "flag": "Watch",
      "trend_template_score": "8/8"
    },
    "NYKAA": {
      "name": "FSN E-Commerce Ventures Ltd",
      "sector": "Consumer Services",
      "close": 322.8,
      "flag": "Watch",
      "trend_template_score": "8/8"
    },
    "PARAS": {
      "name": "Paras Defence and Space Technologies Ltd",
      "sector": "Capital Goods",
      "close": 1195.2,
      "flag": "Watch",
      "trend_template_score": "8/8"
    },
    "MAFANG": {
      "name": "Mirae Asset NYSE FANG+ ETF",
      "sector": null,
      "close": 196.13,
      "flag": "Watch",
      "trend_template_score": "8/8"
    },
    "UFBL": {
      "name": "United Foodbrands Ltd",
      "sector": "Consumer Services",
      "close": 674.85,
      "flag": "Watch",
      "trend_template_score": "8/8"
    },
    "NAZARA": {
      "name": "Nazara Technologies Ltd",
      "sector": "Media, Entertainment &amp; Publication",
      "close": 302.3,
      "flag": "Watch",
      "trend_template_score": "8/8"
    },
    "GLAND": {
      "name": "Gland Pharma Ltd",
      "sector": "Healthcare",
      "close": 2379.8,
      "flag": "Watch",
      "trend_template_score": "8/8"
    },
    "EQUITASBNK": {
      "name": "Equitas Small Finance Bank Ltd",
      "sector": "Financial Services",
      "close": 78.34,
      "flag": "Watch",
      "trend_template_score": "8/8"
    },
    "ASTERDM": {
      "name": "Aster DM Healthcare Ltd",
      "sector": "Healthcare",
      "close": 785.65,
      "flag": "Watch",
      "trend_template_score": "8/8"
    },
    "ABCAPITAL": {
      "name": "Aditya Birla Capital Ltd",
      "sector": "Financial Services",
      "close": 393.85,
      "flag": "Watch",
      "trend_template_score": "8/8"
    },
    "LLOYDSENGG": {
      "name": "Lloyds Engineering Works Ltd",
      "sector": "Capital Goods",
      "close": 88.42,
      "flag": "Watch",
      "trend_template_score": "8/8"
    },
    "ZENTEC": {
      "name": "Zen Technologies Limited",
      "sector": "Capital Goods",
      "close": 1768.7,
      "flag": "Watch",
      "trend_template_score": "8/8"
    },
    "LTF": {
      "name": "L&T Finance Ltd",
      "sector": "Financial Services",
      "close": 302.4,
      "flag": "Watch",
      "trend_template_score": "8/8"
    },
    "JAMNAAUTO": {
      "name": "Jamna Auto Industries Limited",
      "sector": "Automobile and Auto Components",
      "close": 132.67,
      "flag": "Watch",
      "trend_template_score": "8/8"
    },
    "WABAG": {
      "name": "Va Tech Wabag Limited",
      "sector": "Utilities",
      "close": 2041.2,
      "flag": "Watch",
      "trend_template_score": "8/8"
    },
    "SHILPAMED": {
      "name": "Shilpa Medicare Limited",
      "sector": "Healthcare",
      "close": 606.2,
      "flag": "Watch",
      "trend_template_score": "8/8"
    },
    "SIGMAADV": {
      "name": "Sigma Advanced System Ltd",
      "sector": "Capital Goods",
      "close": 523,
      "flag": "Watch",
      "trend_template_score": "8/8"
    },
    "PHOENIXLTD": {
      "name": "The Phoenix Mills Limited",
      "sector": "Realty",
      "close": 2010.7,
      "flag": "Watch",
      "trend_template_score": "8/8"
    },
    "WELSPUNLIV": {
      "name": "Welspun Living Ltd",
      "sector": "Textiles",
      "close": 162,
      "flag": "Watch",
      "trend_template_score": "8/8"
    },
    "RADICO": {
      "name": "Radico Khaitan Limited",
      "sector": "Fast Moving Consumer Goods",
      "close": 4091.3,
      "flag": "Watch",
      "trend_template_score": "8/8"
    },
    "KIRLOSENG": {
      "name": "Kirloskar Oil Engines Limited",
      "sector": "Capital Goods",
      "close": 2182.5,
      "flag": "Watch",
      "trend_template_score": "8/8"
    },
    "SKMEGGPROD": {
      "name": "Skm Egg Products Export (india) Limited",
      "sector": "Fast Moving Consumer Goods",
      "close": 324.75,
      "flag": "Watch",
      "trend_template_score": "8/8"
    },
    "APOLLOHOSP": {
      "name": "Apollo Hospitals Enterprise Limited",
      "sector": "Healthcare",
      "close": 8805.5,
      "flag": "Watch",
      "trend_template_score": "8/8"
    },
    "ARVIND": {
      "name": "Arvind Limited",
      "sector": "Textiles",
      "close": 527.2,
      "flag": "Watch",
      "trend_template_score": "8/8"
    },
    "AARTIIND": {
      "name": "Aarti Industries Limited",
      "sector": "Chemicals",
      "close": 477.8,
      "flag": "Watch",
      "trend_template_score": "7/8"
    },
    "JINDALSAW": {
      "name": "Jindal Saw Limited",
      "sector": "Capital Goods",
      "close": 255.35,
      "flag": "Watch",
      "trend_template_score": "8/8"
    },
    "INDSWFTLAB": {
      "name": "Ind-swift Laboratories Limited",
      "sector": "Healthcare",
      "close": 227.49,
      "flag": "Watch",
      "trend_template_score": "8/8"
    },
    "JAYBARMARU": {
      "name": "Jay Bharat Maruti Limited",
      "sector": "Automobile and Auto Components",
      "close": 161.36,
      "flag": "Watch",
      "trend_template_score": "8/8"
    },
    "USHAMART": {
      "name": "Usha Martin Limited",
      "sector": "Capital Goods",
      "close": 495.7,
      "flag": "Watch",
      "trend_template_score": "8/8"
    },
    "AUROPHARMA": {
      "name": "Aurobindo Pharma Limited",
      "sector": "Healthcare",
      "close": 1532,
      "flag": "Watch",
      "trend_template_score": "8/8"
    },
    "BHARATFORG": {
      "name": "Bharat Forge Limited",
      "sector": "Automobile and Auto Components",
      "close": 2151.6,
      "flag": "Watch",
      "trend_template_score": "8/8"
    },
    "CUMMINSIND": {
      "name": "Cummins India Limited",
      "sector": "Capital Goods",
      "close": 5600.5,
      "flag": "Away",
      "trend_template_score": "7/8"
    }
  }
}